[{"name":"vc.builder.install","duration":4027262,"timestamp":425850528387,"id":"b569f643-fcf4-4476-9084-fab5e54708fb","parentId":"af1a4198-648d-4b8c-93fa-5e1b36f8dc2d","tags":{"cliType":"npm","lockfileVersion":"3","installCommand":"npm install --legacy-peer-deps"},"startTime":1758666001852},{"name":"vc.builder.build","duration":38655263,"timestamp":425854557900,"id":"d51178bb-f2e9-440f-9658-c273cbf818b7","parentId":"af1a4198-648d-4b8c-93fa-5e1b36f8dc2d","tags":{"buildCommand":"npm run build:safe","buildScriptName":"build"},"startTime":1758666005881},{"name":"vc.builder","duration":46143129,"timestamp":425850511680,"id":"af1a4198-648d-4b8c-93fa-5e1b36f8dc2d","parentId":"684b45d6-3c0f-4372-9624-a5e2f96b2143","tags":{"name":"@vercel/next","install":"true","build":"true"},"startTime":1758666001835},{"name":"vc.builder.diagnostics","duration":928,"timestamp":425896655606,"id":"37d9897c-0433-4739-8483-3e766d1ba1af","parentId":"af1a4198-648d-4b8c-93fa-5e1b36f8dc2d","tags":{},"startTime":1758666047980},{"name":"vc.builder.writeBuildResult","duration":1975239,"timestamp":425896656584,"id":"c7d1566d-347b-435d-8e4f-a3fe8d6bc0d8","parentId":"af1a4198-648d-4b8c-93fa-5e1b36f8dc2d","tags":{"buildOutputLength":"1"},"startTime":1758666047981},{"name":"vc.doBuild","duration":48388354,"timestamp":425850324641,"id":"684b45d6-3c0f-4372-9624-a5e2f96b2143","parentId":"a44684a2-969a-46c5-911b-dd6d32e3cec6","tags":{},"startTime":1758666001648},{"name":"vc","duration":48402674,"timestamp":425850310342,"id":"a44684a2-969a-46c5-911b-dd6d32e3cec6","tags":{},"startTime":1758666001634}]