{
  "hidratacao": {
    "name": "Produtos de Hidratação",
    "mappedCategory": "cabelo",
    "icon": "💧",
    "products": [
      {
        "id": "bioextratus-oleo-argan",
        "name": "Bio Extratus Óleo de Argan Premium",
        "mappedCategory": "cabelo"
      },
      {
        "id": "bioextratus-mascara-hidratante",
        "name": "Bio Extratus Máscara Hidratante Multi-Função",
        "mappedCategory": "cabelo"
      },
      {
        "id": "cronograma-capilar-completo",
        "name": "Kit Cronograma Capilar Completo",
        "mappedCategory": "cabelo"
      },
      {
        "id": "tratamento-intensivo-reparacao",
        "name": "Tratamento Intensivo de Reparação",
        "mappedCategory": "cabelo"
      },
      {
        "id": "linha-professional-salon",
        "name": "Linha Professional Salon",
        "mappedCategory": "cabelo"
      }
    ]
  },
  "tintas-loreal": {
    "name": "Tintas L'Oréal",
    "mappedCategory": "tintas",
    "icon": "🎨",
    "products": [
      {
        "id": "loreal-coloracao-premium",
        "name": "L'Oréal Coloração Premium Excellence",
        "mappedCategory": "tintas"
      },
      {
        "id": "loreal-tons-naturais",
        "name": "L'Oréal Tons Naturais Collection",
        "mappedCategory": "tintas"
      },
      {
        "id": "loreal-tons-fashion",
        "name": "L'Oréal Fashion Colors",
        "mappedCategory": "tintas"
      },
      {
        "id": "loreal-professional-salon",
        "name": "L'Oréal Professional Salon Collection",
        "mappedCategory": "tintas"
      },
      {
        "id": "loreal-platinados-especiais",
        "name": "L'Oréal Platinados Especiais",
        "mappedCategory": "tintas"
      },
      {
        "id": "loreal-classic-collection",
        "name": "L'Oréal Classic Collection",
        "mappedCategory": "tintas"
      }
    ]
  },
  "tintas-amend": {
    "name": "Tintas Amend",
    "mappedCategory": "tintas",
    "icon": "🌿",
    "products": [
      {
        "id": "amend-naturals-collection",
        "name": "Amend Naturals Collection",
        "mappedCategory": "tintas"
      },
      {
        "id": "amend-professional-line",
        "name": "Amend Professional Line",
        "mappedCategory": "tintas"
      }
    ]
  },
  "tintas-beauty-color": {
    "name": "Tintas Beauty Color",
    "mappedCategory": "tintas",
    "icon": "💎",
    "products": [
      {
        "id": "beauty-color-kit-coloracao",
        "name": "Beauty Color Kit Coloração Completo",
        "mappedCategory": "tintas"
      },
      {
        "id": "beauty-color-tons-especiais",
        "name": "Beauty Color Tons Especiais",
        "mappedCategory": "tintas"
      },
      {
        "id": "beauty-color-basicos-essenciais",
        "name": "Beauty Color Básicos Essenciais",
        "mappedCategory": "tintas"
      },
      {
        "id": "beauty-color-premium-line",
        "name": "Beauty Color Premium Line",
        "mappedCategory": "tintas"
      }
    ]
  },
  "tintas-biocolor": {
    "name": "Tintas Biocolor",
    "mappedCategory": "tintas",
    "icon": "🌱",
    "products": [
      {
        "id": "biocolor-natural-collection",
        "name": "Biocolor Natural Collection",
        "mappedCategory": "tintas"
      },
      {
        "id": "biocolor-cobertura-total",
        "name": "Biocolor Cobertura Total",
        "mappedCategory": "tintas"
      },
      {
        "id": "biocolor-tons-escuros",
        "name": "Biocolor Tons Escuros",
        "mappedCategory": "tintas"
      },
      {
        "id": "biocolor-linha-premium",
        "name": "Biocolor Linha Premium",
        "mappedCategory": "tintas"
      },
      {
        "id": "biocolor-especiais-festas",
        "name": "Biocolor Especiais para Festas",
        "mappedCategory": "tintas"
      }
    ]
  },
  "tintas-wella": {
    "name": "Tintas Wella",
    "mappedCategory": "tintas",
    "icon": "⭐",
    "products": [
      {
        "id": "wella-koleston-perfect",
        "name": "Wella Koleston Perfect",
        "mappedCategory": "tintas"
      },
      {
        "id": "wella-color-touch",
        "name": "Wella Color Touch",
        "mappedCategory": "tintas"
      },
      {
        "id": "wella-illumina-color",
        "name": "Wella Illumina Color",
        "mappedCategory": "tintas"
      },
      {
        "id": "wella-blondor-multi",
        "name": "Wella Blondor Multi Blonde",
        "mappedCategory": "tintas"
      },
      {
        "id": "wella-professionals-collection",
        "name": "Wella Professionals Collection",
        "mappedCategory": "tintas"
      }
    ]
  },
  "tintas-nutrisse": {
    "name": "Tintas Nutrisse Garnier",
    "mappedCategory": "tintas",
    "icon": "🥑",
    "products": [
      {
        "id": "garnier-nutrisse-creme",
        "name": "Garnier Nutrisse Creme",
        "mappedCategory": "tintas"
      },
      {
        "id": "garnier-nutrisse-ultra-color",
        "name": "Garnier Nutrisse Ultra Color",
        "mappedCategory": "tintas"
      }
    ]
  },
  "progressivas": {
    "name": "Progressivas e Alisamentos",
    "mappedCategory": "progressivas",
    "icon": "✨",
    "products": [
      {
        "id": "progressiva-organica-zap",
        "name": "Zap Professional All Time Organic",
        "mappedCategory": "progressivas"
      },
      {
        "id": "cadiveu-plastica-dos-fios",
        "name": "Cadiveu Plástica dos Fios",
        "mappedCategory": "progressivas"
      },
      {
        "id": "inoar-moroccan-keratin",
        "name": "Inoar Moroccan Keratin",
        "mappedCategory": "progressivas"
      },
      {
        "id": "forever-liss-btox-zero",
        "name": "Forever Liss BTox Zero",
        "mappedCategory": "progressivas"
      },
      {
        "id": "richee-bioplastica",
        "name": "Richée Bioplástica Capilar",
        "mappedCategory": "progressivas"
      },
      {
        "id": "ybera-paris-discovery",
        "name": "Ybera Paris Discovery",
        "mappedCategory": "progressivas"
      }
    ]
  },
  "relaxamentos": {
    "name": "Relaxamentos",
    "mappedCategory": "relaxamentos",
    "icon": "🌊",
    "products": [
      {
        "id": "afro-nature-guanidina",
        "name": "Afro Nature Guanidina Super",
        "mappedCategory": "relaxamentos"
      },
      {
        "id": "salon-line-relaxamento",
        "name": "Salon Line Relaxamento Óleo de Coco",
        "mappedCategory": "relaxamentos"
      },
      {
        "id": "soft-hair-olive",
        "name": "Soft Hair Relaxamento Olive",
        "mappedCategory": "relaxamentos"
      },
      {
        "id": "embelleze-novex",
        "name": "Embelleze Novex Relaxamento",
        "mappedCategory": "relaxamentos"
      },
      {
        "id": "tcb-professional",
        "name": "TCB Professional Relaxamento",
        "mappedCategory": "relaxamentos"
      }
    ]
  }
}